odoo/addons/shopfloor_single_product_transfer_unique_order_at_location/README.rst
odoo/addons/shopfloor_single_product_transfer_unique_order_at_location/__init__.py
odoo/addons/shopfloor_single_product_transfer_unique_order_at_location/__manifest__.py
odoo/addons/shopfloor_single_product_transfer_unique_order_at_location/i18n/it.po
odoo/addons/shopfloor_single_product_transfer_unique_order_at_location/i18n/shopfloor_single_product_transfer_unique_order_at_location.pot
odoo/addons/shopfloor_single_product_transfer_unique_order_at_location/readme/CONTRIBUTORS.rst
odoo/addons/shopfloor_single_product_transfer_unique_order_at_location/readme/DESCRIPTION.rst
odoo/addons/shopfloor_single_product_transfer_unique_order_at_location/services/__init__.py
odoo/addons/shopfloor_single_product_transfer_unique_order_at_location/services/single_product_transfer.py
odoo/addons/shopfloor_single_product_transfer_unique_order_at_location/static/description/icon.png
odoo/addons/shopfloor_single_product_transfer_unique_order_at_location/static/description/index.html
odoo/addons/shopfloor_single_product_transfer_unique_order_at_location/tests/__init__.py
odoo/addons/shopfloor_single_product_transfer_unique_order_at_location/tests/test_set_quantity.py
odoo14_addon_shopfloor_single_product_transfer_unique_order_at_location-14.0.1.2.0.dist-info/METADATA
odoo14_addon_shopfloor_single_product_transfer_unique_order_at_location-14.0.1.2.0.dist-info/WHEEL
odoo14_addon_shopfloor_single_product_transfer_unique_order_at_location-14.0.1.2.0.dist-info/top_level.txt
odoo14_addon_shopfloor_single_product_transfer_unique_order_at_location-14.0.1.2.0.dist-info/RECORD
