Metadata-Version: 2.1
Name: odoo14-addon-shopfloor-single-product-transfer-unique-order-at-location
Version: 14.0.1.2.0
Summary: Prevent to mix sales order on same consolidation location.
Home-page: https://github.com/OCA/wms
Author: Camptocamp, Odoo Community Association (OCA)
Author-email: support@odoo-community.org
License: AGPL-3
Platform: UNKNOWN
Classifier: Programming Language :: Python
Classifier: Framework :: Odoo
Classifier: Framework :: Odoo :: 14.0
Classifier: License :: OSI Approved :: GNU Affero General Public License v3
Requires-Python: >=3.6
Requires-Dist: odoo14-addon-shopfloor-single-product-transfer
Requires-Dist: odoo14-addon-stock-unique-order-per-location
Requires-Dist: odoo <14.1dev,>=14.0a
